<?xml version="1.0" encoding="UTF-8"?>
<services-config>

    <services>
        <service-include file-path="remoting-config.xml"/>
    </services>

    <channel-definition id="my-amf" class="mx.messaging.channels.AMFChannel">
        <endpoint url="http://{server.name}:{server.port}/{context.root}/messagebroker/amf"
            class="flex.messaging.endpoints.AMFEndpoint"/>
        <properties>
            <polling-enabled>false</polling-enabled>
        </properties>
    </channel-definition>

</services-config>